openpivgui/AddInHandler.py
openpivgui/CreateToolTip.py
openpivgui/ErrorChecker.py
openpivgui/MultiProcessing.py
openpivgui/OpenPivGui.py
openpivgui/OpenPivParams.py
openpivgui/PostProcessing.py
openpivgui/PreProcessing.py
openpivgui/__init__.py
openpivgui/open_piv_gui_tools.py
openpivgui/vec_plot.py
openpivgui/AddIns/AddIn.py
openpivgui/AddIns/__init__.py
openpivgui/AddIns/advanced_filtering_addin_preprocessing.py
openpivgui/AddIns/pandas_plotting_addin_plotting.py
openpivgui/AddIns/repl_outliers_addin_postprocessing.py
openpivgui/AddIns/sig2noise_addin_postprocessing.py
openpivgui/AddIns/streamlines_plotting_addin_plotting.py
openpivgui/AddIns/user_function_addin_other.py
openpivgui/res/icon.png
openpivgui-0.4.14.dist-info/LICENCE
openpivgui-0.4.14.dist-info/METADATA
openpivgui-0.4.14.dist-info/WHEEL
openpivgui-0.4.14.dist-info/top_level.txt
openpivgui-0.4.14.dist-info/RECORD
