Metadata-Version: 2.1
Name: openpivgui
Version: 0.4.14
Summary: A simple GUI for Open PIV.
Home-page: https://github.com/OpenPIV/openpiv_tk_gui
Author: P. Vennemann and contributors.
Author-email: vennemann@fh-muenster.de
Classifier: Programming Language :: Python :: 3
Classifier: License :: OSI Approved :: GNU General Public License (GPL)
Classifier: Operating System :: OS Independent
Requires-Python: >=3.0
License-File: LICENCE
Requires-Dist: OpenPiv (==0.23.8)
Requires-Dist: pandas
